README.rst
setup.py
beets_bbq.egg-info/PKG-INFO
beets_bbq.egg-info/SOURCES.txt
beets_bbq.egg-info/dependency_links.txt
beets_bbq.egg-info/namespace_packages.txt
beets_bbq.egg-info/requires.txt
beets_bbq.egg-info/top_level.txt
beetsplug/__init__.py
beetsplug/bbq.py