Metadata-Version: 1.1
Name: beets-bbq
Version: 0.0.1
Summary: blackbird style search query plugin for beets
Home-page: https://github.com/lepisma/beets-bbq
Author: UNKNOWN
Author-email: UNKNOWN
License: UNKNOWN
Keywords: beets plugin search music
Platform: UNKNOWN
Classifier: License :: OSI Approved :: GNU General Public License v3 (GPLv3)
Classifier: Natural Language :: English
Classifier: Programming Language :: Python
Classifier: Programming Language :: Python :: 3 :: Only
